numpy_sugar/__init__.py
numpy_sugar/_array.py
numpy_sugar/_rankdata.py
numpy_sugar/_testit.py
numpy_sugar/epsilon.py
numpy_sugar/linalg/__init__.py
numpy_sugar/linalg/_kron.py
numpy_sugar/linalg/cho.py
numpy_sugar/linalg/det.py
numpy_sugar/linalg/diag.py
numpy_sugar/linalg/dot.py
numpy_sugar/linalg/lstsq.py
numpy_sugar/linalg/lu.py
numpy_sugar/linalg/property.py
numpy_sugar/linalg/qs.py
numpy_sugar/linalg/solve.py
numpy_sugar/linalg/svd.py
numpy_sugar/linalg/test/__init__.py
numpy_sugar/linalg/test/test_linalg.py
numpy_sugar/linalg/tri.py
numpy_sugar/ma/__init__.py
numpy_sugar/ma/dot.py
numpy_sugar/ma/test/__init__.py
numpy_sugar/ma/test/test_dot.py
numpy_sugar/random/__init__.py
numpy_sugar/random/mv.py
numpy_sugar/special/__init__.py
numpy_sugar-1.5.5.dist-info/LICENSE.md
numpy_sugar-1.5.5.dist-info/METADATA
numpy_sugar-1.5.5.dist-info/WHEEL
numpy_sugar-1.5.5.dist-info/RECORD
