Metadata-Version: 2.1
Name: numpy-sugar
Version: 1.5.5
Summary: Missing NumPy functionalities
Home-page: https://github.com/limix/numpy-sugar
License: MIT
Author: Danilo Horta
Author-email: danilo.horta@pm.me
Requires-Python: >=3.10,<4.0
Classifier: License :: OSI Approved :: MIT License
Classifier: Programming Language :: Python :: 3
Classifier: Programming Language :: Python :: 3.10
Classifier: Programming Language :: Python :: 3.11
Classifier: Programming Language :: Python :: 3.12
Classifier: Programming Language :: Python :: 3.13
Requires-Dist: numpy (>=2.2.1,<3.0.0)
Requires-Dist: scipy (>=1.15.0,<2.0.0)
Project-URL: Repository, https://github.com/limix/numpy-sugar
